github_rest_api/__init__.py
github_rest_api/actions/__init__.py
github_rest_api/actions/cargo/__init__.py
github_rest_api/actions/cargo/benchmark.py
github_rest_api/actions/cargo/profiling.py
github_rest_api/actions/cargo/utils.py
github_rest_api/actions/utils.py
github_rest_api/github.py
github_rest_api/utils.py
github_rest_api-0.25.0.dist-info/METADATA
github_rest_api-0.25.0.dist-info/WHEEL
github_rest_api-0.25.0.dist-info/RECORD
