Metadata-Version: 2.1
Name: github-rest-api
Version: 0.25.0
Summary: Simple wrapper of GitHub REST APIs.
Author: Ben Du
Author-email: longendu@yahoo.com
Requires-Python: >=3.10,<4
Classifier: Programming Language :: Python :: 3
Classifier: Programming Language :: Python :: 3.10
Classifier: Programming Language :: Python :: 3.11
Requires-Dist: psutil (>=5.9.4)
Requires-Dist: requests (>=2.28.2)
